celeste_byteplus/__init__.py
celeste_byteplus/py.typed
celeste_byteplus/images/__init__.py
celeste_byteplus/images/client.py
celeste_byteplus/images/config.py
celeste_byteplus/images/parameters.py
celeste_byteplus/images/streaming.py
celeste_byteplus/videos/__init__.py
celeste_byteplus/videos/client.py
celeste_byteplus/videos/config.py
celeste_byteplus/videos/parameters.py
celeste_byteplus-0.3.6.dist-info/METADATA
celeste_byteplus-0.3.6.dist-info/WHEEL
celeste_byteplus-0.3.6.dist-info/RECORD
